{
    "latitude": 40.710335,
    "longitude": -73.99308,
    "generationtime_ms": 0.33724308013916016,
    "utc_offset_seconds": -14400,
    "timezone": "America/New_York",
    "timezone_abbreviation": "GMT-4",
    "elevation": 7.0,
    "hourly_units": {
        "time": "iso8601",
        "temperature_2m": "°F",
        "relativehumidity_2m": "%",
        "dewpoint_2m": "°F",
        "apparent_temperature": "°F",
        "precipitation_probability": "%",
        "rain": "inch",
        "showers": "inch",
        "snowfall": "inch",
        "surface_pressure": "hPa",
        "cloudcover": "%",
        "windspeed_10m": "mp/h",
        "winddirection_10m": "°",
        "windgusts_10m": "mp/h"
    },
    "hourly": {
        "time": [
            "2026-04-03T00:00",
            "2026-04-03T01:00",
            "2026-04-03T02:00",
            "2026-04-03T03:00",
            "2026-04-03T04:00",
            "2026-04-03T05:00",
            "2026-04-03T06:00",
            "2026-04-03T07:00",
            "2026-04-03T08:00",
            "2026-04-03T09:00",
            "2026-04-03T10:00",
            "2026-04-03T11:00",
            "2026-04-03T12:00",
            "2026-04-03T13:00",
            "2026-04-03T14:00",
            "2026-04-03T15:00",
            "2026-04-03T16:00",
            "2026-04-03T17:00",
            "2026-04-03T18:00",
            "2026-04-03T19:00",
            "2026-04-03T20:00",
            "2026-04-03T21:00",
            "2026-04-03T22:00",
            "2026-04-03T23:00"
        ],
        "temperature_2m": [
            41.3,
            41.0,
            41.1,
            40.8,
            40.9,
            41.3,
            42.1,
            41.7,
            42.6,
            43.6,
            44.2,
            46.6,
            49.7,
            51.9,
            55.7,
            60.1,
            62.0,
            64.3,
            66.1,
            64.2,
            60.7,
            60.7,
            59.6,
            59.7
        ],
        "relativehumidity_2m": [
            94,
            95,
            95,
            97,
            96,
            96,
            95,
            97,
            97,
            96,
            99,
            99,
            93,
            88,
            83,
            79,
            74,
            71,
            69,
            74,
            83,
            76,
            84,
            81
        ],
        "dewpoint_2m": [
            39.7,
            39.7,
            39.8,
            40.0,
            39.8,
            40.2,
            40.7,
            40.9,
            41.8,
            42.5,
            44.0,
            46.3,
            47.8,
            48.4,
            50.7,
            53.5,
            53.6,
            54.7,
            55.6,
            55.7,
            55.5,
            53.1,
            54.8,
            53.9
        ],
        "apparent_temperature": [
            36.0,
            36.0,
            36.0,
            36.2,
            36.5,
            36.9,
            38.2,
            38.2,
            39.8,
            40.9,
            41.7,
            44.7,
            46.1,
            48.4,
            52.3,
            56.9,
            58.5,
            61.9,
            64.4,
            63.8,
            60.5,
            59.6,
            59.2,
            59.6
        ],
        "precipitation_probability": [
            2,
            2,
            3,
            4,
            2,
            0,
            1,
            0,
            0,
            0,
            0,
            0,
            0,
            0,
            0,
            0,
            0,
            0,
            1,
            1,
            0,
            0,
            0,
            0
        ],
        "rain": [
            0.0,
            0.0,
            0.0,
            0.0,
            0.004,
            0.0,
            0.0,
            0.0,
            0.0,
            0.0,
            0.0,
            0.0,
            0.0,
            0.0,
            0.0,
            0.0,
            0.0,
            0.0,
            0.0,
            0.0,
            0.0,
            0.0,
            0.0,
            0.0
        ],
        "showers": [
            0.0,
            0.0,
            0.0,
            0.0,
            0.0,
            0.0,
            0.0,
            0.0,
            0.0,
            0.0,
            0.0,
            0.0,
            0.0,
            0.0,
            0.0,
            0.0,
            0.0,
            0.0,
            0.0,
            0.0,
            0.0,
            0.0,
            0.0,
            0.0
        ],
        "snowfall": [
            0.0,
            0.0,
            0.0,
            0.0,
            0.0,
            0.0,
            0.0,
            0.0,
            0.0,
            0.0,
            0.0,
            0.0,
            0.0,
            0.0,
            0.0,
            0.0,
            0.0,
            0.0,
            0.0,
            0.0,
            0.0,
            0.0,
            0.0,
            0.0
        ],
        "surface_pressure": [
            1029.9,
            1029.7,
            1029.5,
            1028.3,
            1028.0,
            1027.3,
            1026.8,
            1026.1,
            1026.0,
            1025.8,
            1025.1,
            1024.6,
            1023.9,
            1023.3,
            1022.2,
            1021.4,
            1020.9,
            1020.5,
            1019.7,
            1019.5,
            1019.0,
            1019.2,
            1019.1,
            1019.0
        ],
        "cloudcover": [
            100,
            100,
            100,
            100,
            100,
            100,
            100,
            100,
            100,
            100,
            100,
            100,
            100,
            100,
            100,
            57,
            20,
            10,
            11,
            30,
            6,
            15,
            100,
            2
        ],
        "windspeed_10m": [
            6.6,
            6.0,
            6.3,
            5.3,
            4.6,
            4.8,
            4.0,
            3.0,
            1.9,
            2.1,
            2.4,
            2.1,
            7.1,
            7.3,
            8.7,
            10.0,
            10.8,
            9.3,
            8.2,
            5.4,
            4.5,
            4.9,
            4.5,
            3.2
        ],
        "winddirection_10m": [
            72,
            63,
            67,
            78,
            43,
            53,
            47,
            48,
            36,
            49,
            292,
            198,
            204,
            211,
            209,
            207,
            198,
            200,
            193,
            185,
            171,
            183,
            171,
            192
        ],
        "windgusts_10m": [
            16.3,
            13.6,
            12.8,
            11.9,
            8.7,
            8.5,
            11.6,
            3.1,
            4.5,
            3.4,
            3.8,
            4.5,
            9.4,
            10.1,
            18.1,
            15.9,
            19.7,
            20.6,
            17.4,
            17.0,
            7.2,
            10.5,
            8.5,
            9.8
        ]
    }
}