{
    "latitude": 40.710335,
    "longitude": -73.99309,
    "generationtime_ms": 0.1016855239868164,
    "utc_offset_seconds": -18000,
    "timezone": "America/New_York",
    "timezone_abbreviation": "GMT-5",
    "elevation": 7.0,
    "hourly_units": {
        "time": "iso8601",
        "temperature_2m": "째F",
        "relativehumidity_2m": "%",
        "dewpoint_2m": "째F",
        "apparent_temperature": "째F",
        "precipitation_probability": "%",
        "rain": "inch",
        "showers": "inch",
        "snowfall": "inch",
        "surface_pressure": "hPa",
        "cloudcover": "%",
        "windspeed_10m": "mp/h",
        "winddirection_10m": "째",
        "windgusts_10m": "mp/h"
    },
    "hourly": {
        "time": [
            "2025-02-01T00:00",
            "2025-02-01T01:00",
            "2025-02-01T02:00",
            "2025-02-01T03:00",
            "2025-02-01T04:00",
            "2025-02-01T05:00",
            "2025-02-01T06:00",
            "2025-02-01T07:00",
            "2025-02-01T08:00",
            "2025-02-01T09:00",
            "2025-02-01T10:00",
            "2025-02-01T11:00",
            "2025-02-01T12:00",
            "2025-02-01T13:00",
            "2025-02-01T14:00",
            "2025-02-01T15:00",
            "2025-02-01T16:00",
            "2025-02-01T17:00",
            "2025-02-01T18:00",
            "2025-02-01T19:00",
            "2025-02-01T20:00",
            "2025-02-01T21:00",
            "2025-02-01T22:00",
            "2025-02-01T23:00"
        ],
        "temperature_2m": [
            46.7,
            47.0,
            46.3,
            44.6,
            42.4,
            39.7,
            39.2,
            38.7,
            36.8,
            36.0,
            36.0,
            35.4,
            36.1,
            37.2,
            37.3,
            36.7,
            35.9,
            32.4,
            29.6,
            29.5,
            27.8,
            26.1,
            25.0,
            23.2
        ],
        "relativehumidity_2m": [
            95,
            96,
            92,
            92,
            87,
            84,
            84,
            81,
            81,
            75,
            60,
            58,
            50,
            44,
            38,
            33,
            29,
            28,
            32,
            32,
            32,
            39,
            41,
            47
        ],
        "dewpoint_2m": [
            45.3,
            45.9,
            44.1,
            42.4,
            38.8,
            35.3,
            34.8,
            33.4,
            31.5,
            28.9,
            23.5,
            22.1,
            19.3,
            17.3,
            14.0,
            10.2,
            6.7,
            2.9,
            3.4,
            3.2,
            1.8,
            4.5,
            4.6,
            5.9
        ],
        "apparent_temperature": [
            43.5,
            44.2,
            42.6,
            38.8,
            34.4,
            30.3,
            30.0,
            29.9,
            26.1,
            25.3,
            24.9,
            24.7,
            25.1,
            26.4,
            26.2,
            24.4,
            24.2,
            20.7,
            17.5,
            17.0,
            16.1,
            15.6,
            15.0,
            13.5
        ],
        "precipitation_probability": [
            69,
            61,
            64,
            31,
            13,
            6,
            0,
            0,
            0,
            0,
            0,
            0,
            0,
            0,
            0,
            0,
            0,
            0,
            0,
            0,
            0,
            0,
            0,
            0
        ],
        "rain": [
            0.012,
            0.008,
            0.008,
            0.0,
            0.0,
            0.0,
            0.0,
            0.0,
            0.0,
            0.0,
            0.0,
            0.0,
            0.0,
            0.0,
            0.0,
            0.0,
            0.0,
            0.0,
            0.0,
            0.0,
            0.0,
            0.0,
            0.0,
            0.0
        ],
        "showers": [
            0.0,
            0.0,
            0.0,
            0.0,
            0.0,
            0.0,
            0.0,
            0.0,
            0.0,
            0.0,
            0.0,
            0.0,
            0.0,
            0.0,
            0.0,
            0.0,
            0.0,
            0.0,
            0.0,
            0.0,
            0.0,
            0.0,
            0.0,
            0.0
        ],
        "snowfall": [
            0.0,
            0.0,
            0.0,
            0.0,
            0.0,
            0.0,
            0.0,
            0.0,
            0.0,
            0.0,
            0.0,
            0.0,
            0.0,
            0.0,
            0.0,
            0.0,
            0.0,
            0.0,
            0.0,
            0.0,
            0.0,
            0.0,
            0.0,
            0.0
        ],
        "surface_pressure": [
            1001.9,
            1001.5,
            1001.9,
            1002.5,
            1003.1,
            1004.3,
            1006.5,
            1008.3,
            1010.4,
            1013.1,
            1015.6,
            1017.6,
            1018.5,
            1019.7,
            1020.4,
            1021.9,
            1023.9,
            1025.3,
            1027.1,
            1028.4,
            1029.3,
            1030.2,
            1031.4,
            1032.2
        ],
        "cloudcover": [
            100,
            100,
            100,
            100,
            100,
            100,
            100,
            100,
            100,
            99,
            49,
            62,
            99,
            99,
            30,
            3,
            5,
            0,
            0,
            0,
            100,
            100,
            100,
            100
        ],
        "windspeed_10m": [
            4.5,
            4.3,
            5.1,
            9.3,
            12.7,
            14.4,
            13.8,
            12.3,
            16.0,
            15.2,
            14.7,
            13.2,
            13.3,
            12.3,
            12.5,
            14.4,
            12.5,
            12.3,
            13.2,
            14.1,
            12.0,
            9.7,
            8.3,
            7.8
        ],
        "winddirection_10m": [
            200,
            270,
            331,
            333,
            332,
            344,
            335,
            338,
            330,
            320,
            329,
            332,
            320,
            315,
            311,
            300,
            310,
            303,
            304,
            317,
            329,
            334,
            336,
            342
        ],
        "windgusts_10m": [
            10.1,
            7.4,
            13.0,
            23.7,
            26.8,
            26.2,
            27.3,
            25.9,
            26.2,
            27.1,
            23.0,
            17.9,
            28.4,
            23.9,
            25.7,
            18.6,
            17.0,
            20.6,
            22.1,
            25.1,
            21.5,
            17.7,
            15.7,
            15.0
        ]
    }
}