{
    "latitude": 40.710335,
    "longitude": -73.99309,
    "generationtime_ms": 0.10228157043457031,
    "utc_offset_seconds": -14400,
    "timezone": "America/New_York",
    "timezone_abbreviation": "GMT-4",
    "elevation": 7.0,
    "hourly_units": {
        "time": "iso8601",
        "temperature_2m": "째F",
        "relativehumidity_2m": "%",
        "dewpoint_2m": "째F",
        "apparent_temperature": "째F",
        "precipitation_probability": "%",
        "rain": "inch",
        "showers": "inch",
        "snowfall": "inch",
        "surface_pressure": "hPa",
        "cloudcover": "%",
        "windspeed_10m": "mp/h",
        "winddirection_10m": "째",
        "windgusts_10m": "mp/h"
    },
    "hourly": {
        "time": [
            "2025-03-15T00:00",
            "2025-03-15T01:00",
            "2025-03-15T02:00",
            "2025-03-15T03:00",
            "2025-03-15T04:00",
            "2025-03-15T05:00",
            "2025-03-15T06:00",
            "2025-03-15T07:00",
            "2025-03-15T08:00",
            "2025-03-15T09:00",
            "2025-03-15T10:00",
            "2025-03-15T11:00",
            "2025-03-15T12:00",
            "2025-03-15T13:00",
            "2025-03-15T14:00",
            "2025-03-15T15:00",
            "2025-03-15T16:00",
            "2025-03-15T17:00",
            "2025-03-15T18:00",
            "2025-03-15T19:00",
            "2025-03-15T20:00",
            "2025-03-15T21:00",
            "2025-03-15T22:00",
            "2025-03-15T23:00"
        ],
        "temperature_2m": [
            41.5,
            41.6,
            42.2,
            41.7,
            41.6,
            41.4,
            41.3,
            41.7,
            42.1,
            41.5,
            43.2,
            43.7,
            45.2,
            45.6,
            46.2,
            47.1,
            46.8,
            45.7,
            44.9,
            45.0,
            45.3,
            46.4,
            47.4,
            47.6
        ],
        "relativehumidity_2m": [
            97,
            93,
            93,
            95,
            96,
            95,
            96,
            94,
            93,
            99,
            92,
            96,
            91,
            92,
            92,
            92,
            94,
            98,
            100,
            100,
            100,
            100,
            99,
            100
        ],
        "dewpoint_2m": [
            40.7,
            39.7,
            40.4,
            40.4,
            40.6,
            40.1,
            40.3,
            40.1,
            40.2,
            41.3,
            41.1,
            42.6,
            42.7,
            43.4,
            44.0,
            44.9,
            45.2,
            45.1,
            44.9,
            45.0,
            45.3,
            46.4,
            47.1,
            47.6
        ],
        "apparent_temperature": [
            36.5,
            36.6,
            37.0,
            36.7,
            37.0,
            36.6,
            36.1,
            37.3,
            37.2,
            36.4,
            38.1,
            38.7,
            40.4,
            41.3,
            42.0,
            43.1,
            43.0,
            41.4,
            40.5,
            40.9,
            41.0,
            42.5,
            43.9,
            44.3
        ],
        "precipitation_probability": [
            0,
            0,
            0,
            0,
            0,
            1,
            1,
            0,
            0,
            0,
            0,
            0,
            0,
            1,
            2,
            1,
            0,
            0,
            1,
            0,
            2,
            2,
            1,
            0
        ],
        "rain": [
            0.0,
            0.0,
            0.0,
            0.0,
            0.0,
            0.0,
            0.0,
            0.0,
            0.0,
            0.0,
            0.0,
            0.0,
            0.0,
            0.0,
            0.0,
            0.0,
            0.0,
            0.0,
            0.0,
            0.0,
            0.0,
            0.0,
            0.0,
            0.0
        ],
        "showers": [
            0.0,
            0.0,
            0.0,
            0.0,
            0.0,
            0.0,
            0.0,
            0.0,
            0.0,
            0.0,
            0.0,
            0.0,
            0.0,
            0.0,
            0.0,
            0.0,
            0.0,
            0.0,
            0.0,
            0.0,
            0.0,
            0.0,
            0.0,
            0.0
        ],
        "snowfall": [
            0.0,
            0.0,
            0.0,
            0.0,
            0.0,
            0.0,
            0.0,
            0.0,
            0.0,
            0.0,
            0.0,
            0.0,
            0.0,
            0.0,
            0.0,
            0.0,
            0.0,
            0.0,
            0.0,
            0.0,
            0.0,
            0.0,
            0.0,
            0.0
        ],
        "surface_pressure": [
            1019.5,
            1019.1,
            1018.9,
            1018.9,
            1018.3,
            1018.5,
            1018.8,
            1019.5,
            1019.8,
            1019.4,
            1019.6,
            1018.6,
            1018.5,
            1019.6,
            1018.8,
            1018.0,
            1017.8,
            1017.9,
            1017.1,
            1016.8,
            1017.2,
            1017.2,
            1016.6,
            1016.7
        ],
        "cloudcover": [
            100,
            100,
            100,
            100,
            100,
            100,
            100,
            100,
            100,
            100,
            100,
            100,
            100,
            100,
            100,
            100,
            100,
            100,
            100,
            100,
            100,
            100,
            100,
            100
        ],
        "windspeed_10m": [
            6.6,
            6.2,
            6.9,
            6.5,
            5.5,
            5.8,
            6.8,
            4.9,
            5.9,
            7.0,
            7.0,
            7.5,
            7.2,
            6.1,
            6.4,
            6.3,
            6.1,
            7.2,
            7.4,
            6.8,
            7.4,
            6.9,
            6.5,
            6.5
        ],
        "winddirection_10m": [
            147,
            136,
            155,
            146,
            137,
            126,
            113,
            133,
            130,
            121,
            135,
            153,
            150,
            172,
            155,
            132,
            126,
            120,
            119,
            134,
            145,
            155,
            149,
            158
        ],
        "windgusts_10m": [
            10.1,
            11.2,
            13.9,
            14.5,
            11.0,
            10.7,
            10.5,
            6.9,
            9.2,
            12.5,
            11.6,
            12.5,
            11.6,
            11.2,
            11.2,
            10.5,
            11.2,
            11.9,
            13.6,
            16.1,
            11.4,
            12.5,
            13.2,
            11.9
        ]
    }
}